gcmpy/__init__.py
gcmpy/covers/__init__.py
gcmpy/covers/eecc.py
gcmpy/distributions/__init__.py
gcmpy/distributions/exponential.py
gcmpy/distributions/poisson.py
gcmpy/distributions/power_law.py
gcmpy/distributions/scale_free_cut_off.py
gcmpy/gcm_algorithm/__init__.py
gcmpy/gcm_algorithm/gcm_algorithm.py
gcmpy/gcm_algorithm/gcm_algorithm_custom_motifs.py
gcmpy/gcm_algorithm/gcm_algorithm_factory.py
gcmpy/gcm_algorithm/gcm_algorithm_fast.py
gcmpy/gcm_algorithm/gcm_algorithm_main.py
gcmpy/gcm_algorithm/gcm_algorithm_network.py
gcmpy/gcm_algorithm/gcm_algorithm_types.py
gcmpy/joint_degree/__init__.py
gcmpy/joint_degree/joint_degree.py
gcmpy/joint_degree/joint_degree_distribution.py
gcmpy/joint_degree/joint_degree_factory.py
gcmpy/joint_degree/joint_degree_type.py
gcmpy/motif_generators/__init__.py
gcmpy/motif_generators/clique_motif.py
gcmpy/motif_generators/cycle_motif.py
gcmpy/motif_generators/diamond_motif.py
gcmpy/names/__init__.py
gcmpy/names/gcm_algorithm_names.py
gcmpy/names/joint_degree_names.py
gcmpy/names/network_names.py
gcmpy/names/tools_names.py
gcmpy/network/__init__.py
gcmpy/network/edge_list.py
gcmpy/network/edge_list_to_network.py
gcmpy/network/network.py
gcmpy/network/network_to_edge_list.py
gcmpy/tools/__init__.py
gcmpy/tools/average_joint_degree_from_jdd.py
gcmpy/tools/draw_set.py
gcmpy/tools/joint_degree_distribution_from_network.py
gcmpy/tools/joint_degree_from_excess.py
gcmpy/tools/joint_excess_from_ejk.py
gcmpy/tools/joint_excess_from_jdd.py
gcmpy/tools/joint_excess_joint_degree.py
gcmpy/tools/joint_excess_joint_degree_keys_view.py
gcmpy/tools/joint_excess_joint_degree_matrices.py
gcmpy/tools/markov_chain_monte_carlo.py
gcmpy/tools/markov_chain_monte_carlo_rewiring.py
gcmpy/tools/proposal_edge.py
gcmpy-0.2.7.dist-info/LICENSE
gcmpy-0.2.7.dist-info/METADATA
gcmpy-0.2.7.dist-info/WHEEL
gcmpy-0.2.7.dist-info/top_level.txt
gcmpy-0.2.7.dist-info/RECORD
