Metadata-Version: 2.1
Name: gcmpy
Version: 0.2.7
Summary: Generalised Configuration Model random graphs in Python
Home-page: https://github.com/PeterStAndrews/gcmpy
Author: Peter Mann
Author-email: pm78@st-andrews.ac.uk
License: License :: OSI Approved :: GNU General Public License v2 or later (GPLv2+)
Platform: UNKNOWN
Classifier: Intended Audience :: Science/Research
Classifier: Intended Audience :: Developers
Classifier: Programming Language :: Python :: 3.8
Classifier: Programming Language :: Python :: 3.9
Classifier: Topic :: Scientific/Engineering
Requires-Python: >=3.8
License-File: LICENSE
Requires-Dist: iteration-utilities (==0.11.0)
Requires-Dist: networkx (==2.6.3)
Requires-Dist: numpy (==1.22.3)
Requires-Dist: setuptools (==60.5.0)
